{"type":"PR","pr":{"number":19,"head":"a59ba7f8d93d156493c3262aa88b8e71716614ab"},"user":"Dave Longley","status":"draft","branch":"cms/lakey-snakey","collection":"post","title":"Pasta Faster","description":"Oh to return to Italy where life is lived at a different pace - Depending on time of day, time of year or time of life the pace will be either frenetic and visceral or slow and thoughtful, . Where all opinions are heard but individualism is not the norm.","objects":{"entry":{"path":"site/content/post/lakey-snakey.md","sha":"4deb5f98e8848206263395106a5e9daf866f0ef6"},"files":[]},"timeStamp":"2019-03-14T20:32:42.456Z"}